yamlns/__init__.py
yamlns/compat.py
yamlns/core.py
yamlns/dateutils.py
yamlns/dateutils_test.py
yamlns/namespace_test.py
yamlns/nstemplate.py
yamlns/nstemplate_test.py
yamlns/pytestutils.py
yamlns/pytestutils_test.py
yamlns/serialization.py
yamlns/testutils.py
yamlns/testutils_test.py
yamlns/_pytestutils_asserts/__init__.py
yamlns/_pytestutils_asserts/assert_impl.py
yamlns/cli/__init__.py
yamlns/cli/json2yaml.py
yamlns/cli/nstemplate.py
yamlns-0.12.4.dist-info/METADATA
yamlns-0.12.4.dist-info/WHEEL
yamlns-0.12.4.dist-info/entry_points.txt
yamlns-0.12.4.dist-info/top_level.txt
yamlns-0.12.4.dist-info/RECORD
