Metadata-Version: 2.4
Name: yamlns
Version: 0.12.4
Summary: YAML serializable dictionary with extra attribute accessors and more
Home-page: https://github.com/GuifiBaix/python-yamlns
Author: David Garcia Garzon
Author-email: voki@canvoki.net
License: GNU General Public License v3 or later (GPLv3+)
Classifier: Programming Language :: Python
Classifier: Programming Language :: Python :: 2
Classifier: Programming Language :: Python :: 3
Classifier: Topic :: Software Development :: Libraries :: Python Modules
Classifier: Framework :: Pytest
Classifier: Intended Audience :: Developers
Classifier: Development Status :: 5 - Production/Stable
Classifier: License :: OSI Approved :: GNU General Public License v3 or later (GPLv3+)
Classifier: Operating System :: OS Independent
Requires-Dist: setuptools>=20.4
Requires-Dist: PyYAML>=5.3.1
Requires-Dist: pytest
Requires-Dist: pytest-cov
Dynamic: author
Dynamic: author-email
Dynamic: classifier
Dynamic: description
Dynamic: description-content-type
Dynamic: home-page
Dynamic: license
Dynamic: requires-dist
Dynamic: summary
